andz/__init__.py
andz/algorithms/README.md
andz/algorithms/__init__.py
andz/algorithms/crypto/README.md
andz/algorithms/crypto/__init__.py
andz/algorithms/crypto/caesar.py
andz/algorithms/crypto/images/block-cipher.png
andz/algorithms/crypto/images/cbc-decryption.png
andz/algorithms/crypto/images/cbc-encryption.png
andz/algorithms/crypto/one_time_pad.py
andz/algorithms/dac/README.md
andz/algorithms/dac/__init__.py
andz/algorithms/dac/binary_search.py
andz/algorithms/dac/find_extrema.py
andz/algorithms/dac/find_peak.py
andz/algorithms/dac/select.py
andz/algorithms/dp/README.md
andz/algorithms/dp/change_making.py
andz/algorithms/dp/fibonacci.py
andz/algorithms/matching/__init__.py
andz/algorithms/matching/gale_shapley.py
andz/algorithms/numerical/README.md
andz/algorithms/numerical/barycentric.py
andz/algorithms/numerical/gradient_descent.py
andz/algorithms/numerical/horner.py
andz/algorithms/numerical/neville.py
andz/algorithms/numerical/newton.py
andz/algorithms/ode/__init__.py
andz/algorithms/ode/forward_euler.py
andz/algorithms/recursion/README.md
andz/algorithms/recursion/__init__.py
andz/algorithms/recursion/ackermann.py
andz/algorithms/recursion/count.py
andz/algorithms/recursion/factorial.py
andz/algorithms/recursion/hanoi.py
andz/algorithms/recursion/is_sorted.py
andz/algorithms/recursion/make_decimal.py
andz/algorithms/recursion/palindrome.py
andz/algorithms/recursion/power.py
andz/algorithms/recursion/reverse.py
andz/algorithms/sorting/README.md
andz/algorithms/sorting/__init__.py
andz/algorithms/sorting/comparison/__init__.py
andz/algorithms/sorting/comparison/bubble_sort.py
andz/algorithms/sorting/comparison/heap_sort.py
andz/algorithms/sorting/comparison/insertion_sort.py
andz/algorithms/sorting/comparison/merge_sort.py
andz/algorithms/sorting/comparison/quick_sort.py
andz/algorithms/sorting/comparison/selection_sort.py
andz/algorithms/sorting/integer/__init__.py
andz/algorithms/sorting/integer/counting_sort.py
andz-0.1.1.dist-info/LICENSE.md
andz-0.1.1.dist-info/METADATA
andz-0.1.1.dist-info/WHEEL
andz-0.1.1.dist-info/RECORD
